slack_emopack/IconFetcher.py
slack_emopack/Importer.py
slack_emopack/__init__.py
slack_emopack/bin.py
slack_emopack-1.0.dist-info/METADATA
slack_emopack-1.0.dist-info/WHEEL
slack_emopack-1.0.dist-info/entry_points.txt
slack_emopack-1.0.dist-info/top_level.txt
slack_emopack-1.0.dist-info/RECORD
